{
  "assignee": "jmush16@gmail.com",
  "claim_note": "",
  "claimed_at": "2026-01-23T15:58:00.078105Z",
  "created_at": "2026-01-23T03:05:39.243446Z",
  "depends_on": [],
  "epic": "fn-1",
  "evidence": {
    "commits": [
      "c275d1ed02e23cb3191b95fa08ff37e5793d297f"
    ],
    "tests": "swift test --filter OpenAIClientAdapter (36 tests passed)"
  },
  "id": "fn-1.21",
  "priority": null,
  "spec_path": ".flow/tasks/fn-1.21.md",
  "status": "done",
  "title": "Task 2.5: OpenAIClientAdapter",
  "updated_at": "2026-01-23T15:58:00.244384Z"
}
